AudioProcessor/AudioProcessor.py
AudioProcessor/__init__.py
AudioProcessor-0.2.1.dist-info/METADATA
AudioProcessor-0.2.1.dist-info/WHEEL
AudioProcessor-0.2.1.dist-info/top_level.txt
AudioProcessor-0.2.1.dist-info/RECORD
